[
    {
        "type": "message",
        "subtype": "bot_message",
        "text": "hi Ra'ed. how's it going?",
        "ts": "1550484203.000100",
        "username": "Alexander Schwank (Prospela Mentors (beta))",
        "icons": {
            "image_48": "https:\/\/s3-us-west-2.amazonaws.com\/slack-files2\/bot_icons\/2019-02-18\/552939910112_48.png"
        },
        "bot_id": "B6CS60LDU"
    },
    {
        "type": "message",
        "subtype": "bot_message",
        "text": "12\/32 levels made!",
        "ts": "1550484524.000200",
        "username": "Ra'ed (Mentee)",
        "icons": {
            "image_48": "https:\/\/s3-us-west-2.amazonaws.com\/slack-files2\/bot_icons\/2019-02-18\/553120228161_48.png"
        },
        "bot_id": "B6CS60LDU"
    },
    {
        "type": "message",
        "subtype": "bot_message",
        "text": "btw the callstack thing is fixed ha",
        "ts": "1550484539.000300",
        "username": "Ra'ed (Mentee)",
        "icons": {
            "image_48": "https:\/\/s3-us-west-2.amazonaws.com\/slack-files2\/bot_icons\/2019-02-18\/553120371745_48.png"
        },
        "bot_id": "B6CS60LDU"
    },
    {
        "type": "message",
        "text": "",
        "files": [
            {
                "id": "FG9GSK691",
                "created": 1550484676,
                "timestamp": 1550484676,
                "name": "ukuh.png",
                "title": "ukuh",
                "mimetype": "image\/png",
                "filetype": "png",
                "pretty_type": "PNG",
                "user": "U6D2VCN07",
                "editable": false,
                "size": 107735,
                "mode": "hosted",
                "is_external": false,
                "external_type": "",
                "is_public": true,
                "public_url_shared": false,
                "display_as_bot": false,
                "username": "",
                "url_private": "https:\/\/files.slack.com\/files-pri\/T4UUTPV18-FG9GSK691\/ukuh.png?t=xoxe-164979811042-1081742544354-1080362743317-fee6284c0ee20406565ca4cadf37d845",
                "url_private_download": "https:\/\/files.slack.com\/files-pri\/T4UUTPV18-FG9GSK691\/download\/ukuh.png?t=xoxe-164979811042-1081742544354-1080362743317-fee6284c0ee20406565ca4cadf37d845",
                "thumb_64": "https:\/\/files.slack.com\/files-tmb\/T4UUTPV18-FG9GSK691-9cd7661b3a\/ukuh_64.png?t=xoxe-164979811042-1081742544354-1080362743317-fee6284c0ee20406565ca4cadf37d845",
                "thumb_80": "https:\/\/files.slack.com\/files-tmb\/T4UUTPV18-FG9GSK691-9cd7661b3a\/ukuh_80.png?t=xoxe-164979811042-1081742544354-1080362743317-fee6284c0ee20406565ca4cadf37d845",
                "thumb_360": "https:\/\/files.slack.com\/files-tmb\/T4UUTPV18-FG9GSK691-9cd7661b3a\/ukuh_360.png?t=xoxe-164979811042-1081742544354-1080362743317-fee6284c0ee20406565ca4cadf37d845",
                "thumb_360_w": 360,
                "thumb_360_h": 213,
                "thumb_480": "https:\/\/files.slack.com\/files-tmb\/T4UUTPV18-FG9GSK691-9cd7661b3a\/ukuh_480.png?t=xoxe-164979811042-1081742544354-1080362743317-fee6284c0ee20406565ca4cadf37d845",
                "thumb_480_w": 480,
                "thumb_480_h": 285,
                "thumb_160": "https:\/\/files.slack.com\/files-tmb\/T4UUTPV18-FG9GSK691-9cd7661b3a\/ukuh_160.png?t=xoxe-164979811042-1081742544354-1080362743317-fee6284c0ee20406565ca4cadf37d845",
                "thumb_720": "https:\/\/files.slack.com\/files-tmb\/T4UUTPV18-FG9GSK691-9cd7661b3a\/ukuh_720.png?t=xoxe-164979811042-1081742544354-1080362743317-fee6284c0ee20406565ca4cadf37d845",
                "thumb_720_w": 720,
                "thumb_720_h": 427,
                "thumb_800": "https:\/\/files.slack.com\/files-tmb\/T4UUTPV18-FG9GSK691-9cd7661b3a\/ukuh_800.png?t=xoxe-164979811042-1081742544354-1080362743317-fee6284c0ee20406565ca4cadf37d845",
                "thumb_800_w": 800,
                "thumb_800_h": 474,
                "thumb_960": "https:\/\/files.slack.com\/files-tmb\/T4UUTPV18-FG9GSK691-9cd7661b3a\/ukuh_960.png?t=xoxe-164979811042-1081742544354-1080362743317-fee6284c0ee20406565ca4cadf37d845",
                "thumb_960_w": 960,
                "thumb_960_h": 569,
                "thumb_1024": "https:\/\/files.slack.com\/files-tmb\/T4UUTPV18-FG9GSK691-9cd7661b3a\/ukuh_1024.png?t=xoxe-164979811042-1081742544354-1080362743317-fee6284c0ee20406565ca4cadf37d845",
                "thumb_1024_w": 1024,
                "thumb_1024_h": 607,
                "image_exif_rotation": 1,
                "original_w": 1476,
                "original_h": 875,
                "permalink": "https:\/\/prospela.slack.com\/files\/U6D2VCN07\/FG9GSK691\/ukuh.png",
                "permalink_public": "https:\/\/slack-files.com\/T4UUTPV18-FG9GSK691-0d6e1ddaa8",
                "is_starred": false,
                "has_rich_preview": false
            }
        ],
        "upload": true,
        "user": "U6D2VCN07",
        "display_as_bot": false,
        "ts": "1550484681.000400"
    },
    {
        "type": "message",
        "subtype": "bot_message",
        "text": "well done!",
        "ts": "1550485269.000700",
        "username": "Alexander Schwank (Prospela Mentors (beta))",
        "icons": {
            "image_48": "https:\/\/s3-us-west-2.amazonaws.com\/slack-files2\/bot_icons\/2019-02-18\/552953560048_48.png"
        },
        "bot_id": "B6CS60LDU"
    },
    {
        "type": "message",
        "subtype": "bot_message",
        "text": "thanks! Its all thanks to c++, cocos2d-x",
        "ts": "1550487222.000800",
        "username": "Ra'ed (Mentee)",
        "icons": {
            "image_48": "https:\/\/s3-us-west-2.amazonaws.com\/slack-files2\/bot_icons\/2019-02-18\/555158566134_48.png"
        },
        "bot_id": "B6CS60LDU"
    },
    {
        "type": "message",
        "subtype": "bot_message",
        "text": "",
        "ts": "1550487273.000900",
        "username": "Ra'ed (Mentee)",
        "icons": {
            "image_48": "https:\/\/s3-us-west-2.amazonaws.com\/slack-files2\/bot_icons\/2019-02-18\/553155361569_48.png"
        },
        "bot_id": "B6CS60LDU",
        "attachments": [
            {
                "author_name": "Ra'ed",
                "author_subname": "Ra'ed",
                "fallback": "[February 18th, 2019 10:11 AM] raedinbox: this is one level.",
                "text": "this is one level.",
                "footer": "Posted in #alex-and-raed",
                "id": 1,
                "author_link": "https:\/\/prospelaautumn2.slack.com\/team\/UDPD23QGG",
                "author_icon": "https:\/\/avatars.slack-edge.com\/2018-10-28\/466183113714_36e67de5bf7da19c4f77_48.jpg",
                "ts": 1550484675,
                "color": "D0D0D0",
                "mrkdwn_in": [
                    "text"
                ]
            }
        ]
    },
    {
        "type": "message",
        "subtype": "bot_message",
        "text": "sorry accident",
        "ts": "1550487282.001000",
        "username": "Ra'ed (Mentee)",
        "icons": {
            "image_48": "https:\/\/s3-us-west-2.amazonaws.com\/slack-files2\/bot_icons\/2019-02-18\/552979403904_48.png"
        },
        "bot_id": "B6CS60LDU"
    }
]