[
    {
        "type": "message",
        "subtype": "bot_message",
        "text": "_Team *Mentee* joined the shared channel_",
        "ts": "1550582138.000800",
        "username": "Smooz",
        "bot_id": "B6CS60LDU"
    },
    {
        "type": "message",
        "subtype": "bot_message",
        "text": "_Team *Mentor* joined the shared channel_",
        "ts": "1550582141.000900",
        "username": "Smooz",
        "bot_id": "B6CS60LDU"
    },
    {
        "type": "message",
        "subtype": "channel_name",
        "ts": "1550582200.001000",
        "user": "U4VR52RQE",
        "text": "<@U4VR52RQE> has renamed the channel from \"z-shared-19\" to \"arran-and-khadijah\"",
        "old_name": "z-shared-19",
        "name": "arran-and-khadijah"
    },
    {
        "type": "message",
        "subtype": "bot_message",
        "text": "_@khadijahbah148 has joined the channel_",
        "ts": "1550582633.001100",
        "username": "smooz (Mentee)",
        "icons": {
            "image_48": "https:\/\/s3-us-west-2.amazonaws.com\/slack-files2\/bot_icons\/2019-02-19\/554152410769_48.png"
        },
        "bot_id": "B6CS60LDU"
    },
    {
        "type": "message",
        "subtype": "bot_message",
        "text": "_@arranlawson has joined the channel_",
        "ts": "1550582639.001200",
        "username": "smooz (Mentor)",
        "icons": {
            "image_48": "https:\/\/s3-us-west-2.amazonaws.com\/slack-files2\/bot_icons\/2019-02-19\/555048223861_48.png"
        },
        "bot_id": "B6CS60LDU"
    },
    {
        "type": "message",
        "subtype": "bot_message",
        "text": "Hey Khadijah, please meet Arran your incredible E-Mentor I've been telling you about :smile:.  Feel free to introduce yourselves, say a little bit about what you would like to get out of the relationship and continue chatting within this channel. :wave:\n\nI will now be leaving the channel, but please direct message myself or emma-prospela if you have any questions. All the best for now! :slightly_smiling_face:",
        "ts": "1550582693.001300",
        "username": "Dexter (Mentee)",
        "icons": {
            "image_48": "https:\/\/s3-us-west-2.amazonaws.com\/slack-files2\/bot_icons\/2019-02-19\/554726439778_48.png"
        },
        "bot_id": "B6CS60LDU"
    },
    {
        "type": "message",
        "subtype": "bot_message",
        "text": "_@dexter has left the channel_",
        "ts": "1550582744.001400",
        "username": "smooz (Mentor)",
        "icons": {
            "image_48": "https:\/\/s3-us-west-2.amazonaws.com\/slack-files2\/bot_icons\/2019-02-19\/554153883825_48.png"
        },
        "bot_id": "B6CS60LDU"
    },
    {
        "type": "message",
        "subtype": "bot_message",
        "text": "_@dexter has left the channel_",
        "ts": "1550582751.001500",
        "username": "smooz (Mentee)",
        "icons": {
            "image_48": "https:\/\/s3-us-west-2.amazonaws.com\/slack-files2\/bot_icons\/2019-02-19\/554680613636_48.png"
        },
        "bot_id": "B6CS60LDU"
    },
    {
        "type": "message",
        "subtype": "bot_message",
        "text": "Hello Khadijah :wave:\nHow are you?\nI've just read through your profile and I'm very impressed :grin:\nIt sounds like you've got a clear idea of what you'd like to do and the career path you're looking to follow...\nMaybe you can tell me a little more about what you'd like to learn through Prospela?\nAlso, I don't know whether Dexter has sent you any information about me... but if you have any questions, feel free to ask :+1:",
        "ts": "1550600213.001600",
        "username": "Arran Lawson (Mentor)",
        "icons": {
            "image_48": "https:\/\/s3-us-west-2.amazonaws.com\/slack-files2\/bot_icons\/2019-02-19\/554933030531_48.png"
        },
        "bot_id": "B6CS60LDU"
    }
]