[
    {
        "type": "message",
        "subtype": "channel_join",
        "ts": "1576148790.000200",
        "user": "U4VR52RQE",
        "text": "<@U4VR52RQE> has joined the channel"
    },
    {
        "type": "message",
        "subtype": "channel_join",
        "ts": "1576148791.000400",
        "user": "U6D2VCN07",
        "text": "<@U6D2VCN07> has joined the channel",
        "inviter": "U4VR52RQE"
    },
    {
        "type": "message",
        "subtype": "bot_message",
        "text": ":champagne: _You have opened a new, empty shared channel._ \n_Share <https:\/\/www.smooz.io\/room\/5df21f369cb7c20004b72901|this link> with other teams to invite them in it_",
        "ts": "1576148791.000500",
        "username": "Smooz",
        "bot_id": "B6CS60LDU"
    },
    {
        "type": "message",
        "subtype": "channel_name",
        "ts": "1576148851.000600",
        "user": "U4VR52RQE",
        "text": "<@U4VR52RQE> has renamed the channel from \"z-shared-23\" to \"nico-and-josh\"",
        "old_name": "z-shared-23",
        "name": "nico-and-josh"
    },
    {
        "type": "message",
        "subtype": "channel_join",
        "ts": "1576148863.000800",
        "user": "U4V22C6A1",
        "text": "<@U4V22C6A1> has joined the channel",
        "inviter": "U4VR52RQE"
    },
    {
        "type": "message",
        "subtype": "bot_message",
        "text": "_Team *Prospela Students (beta)* joined the shared channel_",
        "ts": "1576148921.000900",
        "username": "Smooz",
        "bot_id": "B6CS60LDU"
    },
    {
        "type": "message",
        "subtype": "bot_message",
        "text": "_Team *Prospela Mentors (beta)* joined the shared channel_",
        "ts": "1576148929.001000",
        "username": "Smooz",
        "bot_id": "B6CS60LDU"
    },
    {
        "type": "message",
        "subtype": "bot_message",
        "text": "_@joshdoesvfx has joined the channel_",
        "ts": "1576149089.001100",
        "username": "smooz (Prospela Students (beta))",
        "icons": {
            "image_48": "https:\/\/s3-us-west-2.amazonaws.com\/slack-files2\/bot_icons\/2019-12-12\/860496850497_48.png"
        },
        "bot_id": "B6CS60LDU"
    },
    {
        "type": "message",
        "subtype": "bot_message",
        "text": "_@devant has joined the channel_",
        "ts": "1576149094.001200",
        "username": "smooz (Prospela Mentors (beta))",
        "icons": {
            "image_48": "https:\/\/s3-us-west-2.amazonaws.com\/slack-files2\/bot_icons\/2019-12-12\/859299915523_48.png"
        },
        "bot_id": "B6CS60LDU"
    },
    {
        "type": "message",
        "subtype": "bot_message",
        "text": "Hey Josh, please meet Luis Nicolas (Nico) your incredible E-Mentor we've been telling you about :smile:.  Feel free to introduce yourselves, say a little bit about what you would like to get out of the mentorship and continue chatting within this channel. :wave:\n\nI will now be leaving the channel, but please direct message myself or penny-prospela if you have any questions. All the best for now! :slightly_smiling_face:",
        "ts": "1576149101.001300",
        "username": "Emma Sullivan (Prospela Students (beta))",
        "icons": {
            "image_48": "https:\/\/s3-us-west-2.amazonaws.com\/slack-files2\/bot_icons\/2019-12-12\/872976671590_48.png"
        },
        "bot_id": "B6CS60LDU"
    },
    {
        "type": "message",
        "subtype": "bot_message",
        "text": "_@emma has left the channel_",
        "ts": "1576149107.001400",
        "username": "smooz (Prospela Students (beta))",
        "icons": {
            "image_48": "https:\/\/s3-us-west-2.amazonaws.com\/slack-files2\/bot_icons\/2019-12-12\/857986113794_48.png"
        },
        "bot_id": "B6CS60LDU"
    },
    {
        "type": "message",
        "subtype": "bot_message",
        "text": "_@emma has left the channel_",
        "ts": "1576149111.001500",
        "username": "smooz (Prospela Mentors (beta))",
        "icons": {
            "image_48": "https:\/\/s3-us-west-2.amazonaws.com\/slack-files2\/bot_icons\/2019-12-12\/870767518304_48.png"
        },
        "bot_id": "B6CS60LDU"
    },
    {
        "type": "message",
        "subtype": "bot_message",
        "text": "Hello Nico, I hope you’re well!",
        "ts": "1576149291.001600",
        "username": "Josh Bagnall (Prospela Students (beta))",
        "icons": {
            "image_48": "https:\/\/s3-us-west-2.amazonaws.com\/slack-files2\/bot_icons\/2019-12-12\/872631515319_48.png"
        },
        "bot_id": "B6CS60LDU"
    },
    {
        "type": "message",
        "subtype": "bot_message",
        "text": "Hey Josh! Sorry for the late Reply, I'm currently in Canada. How are you? Let me know what I can help you with :)",
        "ts": "1576160211.001700",
        "username": "Nico Coronado (Prospela Mentors (beta))",
        "icons": {
            "image_48": "https:\/\/s3-us-west-2.amazonaws.com\/slack-files2\/bot_icons\/2019-11-28\/855405348806_48.png"
        },
        "bot_id": "B6CS60LDU"
    },
    {
        "type": "message",
        "subtype": "bot_message",
        "text": "I’m good thank you, how are you? I’m just really looking for some guidance and help with compositing in general, I’ve only recently started doing a few online courses for Nuke etc. I also work in a creative studio where we do a lot of VFX stuff, so I’m really looking to develop my skills in this field  :slightly_smiling_face:",
        "ts": "1576160854.001800",
        "username": "Josh Bagnall (Prospela Students (beta))",
        "icons": {
            "image_48": "https:\/\/s3-us-west-2.amazonaws.com\/slack-files2\/bot_icons\/2019-12-12\/860739488513_48.png"
        },
        "bot_id": "B6CS60LDU"
    },
    {
        "type": "message",
        "subtype": "bot_message",
        "text": "Cool stuff, sounds like a good starting point :) if you ever have questions or want some feedback in your work, you can count with me.",
        "ts": "1576161091.001900",
        "username": "Nico Coronado (Prospela Mentors (beta))",
        "icons": {
            "image_48": "https:\/\/s3-us-west-2.amazonaws.com\/slack-files2\/bot_icons\/2019-12-12\/860746719841_48.png"
        },
        "bot_id": "B6CS60LDU"
    },
    {
        "type": "message",
        "subtype": "bot_message",
        "text": "That’s great Nico, thank you! How’s Canada?",
        "ts": "1576161304.002000",
        "username": "Josh Bagnall (Prospela Students (beta))",
        "icons": {
            "image_48": "https:\/\/s3-us-west-2.amazonaws.com\/slack-files2\/bot_icons\/2019-12-12\/873232074422_48.png"
        },
        "bot_id": "B6CS60LDU"
    },
    {
        "type": "message",
        "subtype": "bot_message",
        "text": "Cold!",
        "ts": "1576161912.002100",
        "username": "Nico Coronado (Prospela Mentors (beta))",
        "icons": {
            "image_48": "https:\/\/s3-us-west-2.amazonaws.com\/slack-files2\/bot_icons\/2019-12-12\/859572786547_48.png"
        },
        "bot_id": "B6CS60LDU"
    },
    {
        "type": "message",
        "subtype": "bot_message",
        "text": "Otherwise alright, Montreal is a strange place.",
        "ts": "1576161947.002200",
        "username": "Nico Coronado (Prospela Mentors (beta))",
        "icons": {
            "image_48": "https:\/\/s3-us-west-2.amazonaws.com\/slack-files2\/bot_icons\/2019-12-12\/860771386913_48.png"
        },
        "bot_id": "B6CS60LDU"
    },
    {
        "type": "message",
        "subtype": "bot_message",
        "text": "I’ve never been, would definitely love to visit. Have you heard about the “rumours” regarding MPC closing their Vancouver Studio?",
        "ts": "1576162260.002300",
        "username": "Josh Bagnall (Prospela Students (beta))",
        "icons": {
            "image_48": "https:\/\/s3-us-west-2.amazonaws.com\/slack-files2\/bot_icons\/2019-12-12\/859583143091_48.png"
        },
        "bot_id": "B6CS60LDU"
    },
    {
        "type": "message",
        "subtype": "bot_message",
        "text": "Yeah. Harsh stuff. But it happens all the time :s",
        "ts": "1576163048.002400",
        "username": "Nico Coronado (Prospela Mentors (beta))",
        "icons": {
            "image_48": "https:\/\/s3-us-west-2.amazonaws.com\/slack-files2\/bot_icons\/2019-12-12\/858295541698_48.png"
        },
        "bot_id": "B6CS60LDU"
    },
    {
        "type": "message",
        "subtype": "bot_message",
        "text": "Things are changing fast. But companies are a different thing to artists. There's always work for us.",
        "ts": "1576163146.002500",
        "username": "Nico Coronado (Prospela Mentors (beta))",
        "icons": {
            "image_48": "https:\/\/s3-us-west-2.amazonaws.com\/slack-files2\/bot_icons\/2019-12-12\/873289121894_48.png"
        },
        "bot_id": "B6CS60LDU"
    },
    {
        "type": "message",
        "subtype": "bot_message",
        "text": "Of course is better to settle in cities with lots of companies and supportive governments. Or be willing to move a lot. Be a wandering artist ha.",
        "ts": "1576163195.002600",
        "username": "Nico Coronado (Prospela Mentors (beta))",
        "icons": {
            "image_48": "https:\/\/s3-us-west-2.amazonaws.com\/slack-files2\/bot_icons\/2019-12-12\/872942073943_48.png"
        },
        "bot_id": "B6CS60LDU"
    },
    {
        "type": "message",
        "subtype": "bot_message",
        "text": "I think it’s crazy a company can just close up shop like that, honestly. But yeah, we have recently had a lot of freelancers in and the majority seem to love it - in comparison to working specifically just for one company full time",
        "ts": "1576163763.002700",
        "username": "Josh Bagnall (Prospela Students (beta))",
        "icons": {
            "image_48": "https:\/\/s3-us-west-2.amazonaws.com\/slack-files2\/bot_icons\/2019-12-12\/858318098738_48.png"
        },
        "bot_id": "B6CS60LDU"
    },
    {
        "type": "message",
        "subtype": "bot_message",
        "text": "Spoke to a guy last night at the Foundry Christmas party who said one of the best things you can do as a young artist is move around and jump between big\/small companies - would you agree?",
        "ts": "1576163817.002800",
        "username": "Josh Bagnall (Prospela Students (beta))",
        "icons": {
            "image_48": "https:\/\/s3-us-west-2.amazonaws.com\/slack-files2\/bot_icons\/2019-12-12\/871111305285_48.png"
        },
        "bot_id": "B6CS60LDU"
    }
]