[
    {
        "type": "message",
        "subtype": "bot_message",
        "text": "Sorry I haven't anything in a while, but been working on my modelling! <https:\/\/twitter.com\/marfo343\/status\/1100165138433355783>",
        "ts": "1553631474.001200",
        "username": "Nana (Prospela Students (beta))",
        "icons": {
            "image_48": "https:\/\/s3-us-west-2.amazonaws.com\/slack-files2\/bot_icons\/2019-03-26\/580210983153_48.png"
        },
        "bot_id": "B6CS60LDU"
    }
]