[
    {
        "type": "message",
        "text": "<@U5Z6RM8R0> \n\nHope the site is coming along nicely for you! I know your mentee hasn't been too engaging, but we still want to say that we have really appreciated having you be part of our 1st Summer E-Mentoring Pilot Study and hope you have enjoyed it too! The students have given us some incredibly *POSITIVE* feedback for all of you Rockstar E-Mentors and hugely appreciate your help!\n\n*We now just need you to complete this quick debrief form (Link is here: <https:\/\/prospela.typeform.com\/to\/wPkrSE>)*\n\nWe want to hear your *HONEST* opinion about the experience. We'll be using your feedback to help us build the product in the future so don't tell us \"It was great\" if you didn't feel that way! \nDon't worry, you won't hurt our feelings :smiley:",
        "user": "U4VR52RQE",
        "ts": "1500643882.682353",
        "team": "T4UUTPV18",
        "user_team": "T4UUTPV18",
        "source_team": "T4UUTPV18",
        "user_profile": {
            "avatar_hash": "d730c1e93535",
            "image_72": "https:\/\/avatars.slack-edge.com\/2017-06-20\/201542361287_d730c1e93535ae06c852_72.png",
            "first_name": "Dexter",
            "real_name": "Dexter",
            "display_name": "dexter-prospela",
            "team": "T4UUTPV18",
            "name": "dexter-prospela",
            "is_restricted": false,
            "is_ultra_restricted": false
        }
    }
]