[
    {
        "type": "message",
        "subtype": "bot_message",
        "text": "sounds good.",
        "ts": "1565706513.002600",
        "username": "Alexander Schwank (Prospela Mentors (beta))",
        "icons": {
            "image_48": "https:\/\/s3-us-west-2.amazonaws.com\/slack-files2\/bot_icons\/2019-08-13\/727137218646_48.png"
        },
        "bot_id": "B6CS60LDU"
    },
    {
        "type": "message",
        "subtype": "bot_message",
        "text": "is there anything in your local community \/ sport \/ family where such an app (doesn't need to be buying, maybe just giving away for free) would help?",
        "ts": "1565706571.002700",
        "username": "Alexander Schwank (Prospela Mentors (beta))",
        "icons": {
            "image_48": "https:\/\/s3-us-west-2.amazonaws.com\/slack-files2\/bot_icons\/2019-08-13\/727138690918_48.png"
        },
        "bot_id": "B6CS60LDU"
    },
    {
        "type": "message",
        "subtype": "bot_message",
        "text": "No..?? I don't know..??",
        "ts": "1565707195.002800",
        "username": "Janies (Mentee)",
        "icons": {
            "image_48": "https:\/\/s3-us-west-2.amazonaws.com\/slack-files2\/bot_icons\/2019-08-13\/725003807840_48.png"
        },
        "bot_id": "B6CS60LDU"
    },
    {
        "type": "message",
        "subtype": "bot_message",
        "text": "Since it doesn't have to be too real, I was thinking something along the lines of a person wants to start their own shopping business, and so wants to set up an app for it",
        "ts": "1565707502.002900",
        "username": "Janies (Mentee)",
        "icons": {
            "image_48": "https:\/\/s3-us-west-2.amazonaws.com\/slack-files2\/bot_icons\/2019-08-13\/725016896789_48.png"
        },
        "bot_id": "B6CS60LDU"
    },
    {
        "type": "message",
        "subtype": "bot_message",
        "text": "I don't know.. That's kinda what I was thinking about",
        "ts": "1565707528.003000",
        "username": "Janies (Mentee)",
        "icons": {
            "image_48": "https:\/\/s3-us-west-2.amazonaws.com\/slack-files2\/bot_icons\/2019-08-13\/725011895920_48.png"
        },
        "bot_id": "B6CS60LDU"
    },
    {
        "type": "message",
        "subtype": "bot_message",
        "text": "ah yes, sure.",
        "ts": "1565707762.003100",
        "username": "Alexander Schwank (Prospela Mentors (beta))",
        "icons": {
            "image_48": "https:\/\/s3-us-west-2.amazonaws.com\/slack-files2\/bot_icons\/2019-08-13\/727168055222_48.png"
        },
        "bot_id": "B6CS60LDU"
    },
    {
        "type": "message",
        "subtype": "bot_message",
        "text": "Do you think it's good enough??",
        "ts": "1565708286.003200",
        "username": "Janies (Mentee)",
        "icons": {
            "image_48": "https:\/\/s3-us-west-2.amazonaws.com\/slack-files2\/bot_icons\/2019-08-13\/726893503943_48.png"
        },
        "bot_id": "B6CS60LDU"
    },
    {
        "type": "message",
        "subtype": "bot_message",
        "text": "I think so yes",
        "ts": "1565708571.003300",
        "username": "Alexander Schwank (Prospela Mentors (beta))",
        "icons": {
            "image_48": "https:\/\/s3-us-west-2.amazonaws.com\/slack-files2\/bot_icons\/2019-08-13\/725044689285_48.png"
        },
        "bot_id": "B6CS60LDU"
    },
    {
        "type": "message",
        "subtype": "bot_message",
        "text": "my only concern is what the brief is asking for",
        "ts": "1565708597.003400",
        "username": "Alexander Schwank (Prospela Mentors (beta))",
        "icons": {
            "image_48": "https:\/\/s3-us-west-2.amazonaws.com\/slack-files2\/bot_icons\/2019-08-13\/724575412836_48.png"
        },
        "bot_id": "B6CS60LDU"
    },
    {
        "type": "message",
        "subtype": "bot_message",
        "text": "do you think you're going to get more details at some point?",
        "ts": "1565708617.003500",
        "username": "Alexander Schwank (Prospela Mentors (beta))",
        "icons": {
            "image_48": "https:\/\/s3-us-west-2.amazonaws.com\/slack-files2\/bot_icons\/2019-08-13\/724576041348_48.png"
        },
        "bot_id": "B6CS60LDU"
    },
    {
        "type": "message",
        "subtype": "bot_message",
        "text": "it's like a typical thing we face - the clients already have a concrete plan in mind but they don't tell you it, they just give you a very short, very broad brief and you're left alone with figuring out what the client is actually after. so you learn quite quickly to ask for more and more details to be sure you know exactly what you are supposed to do",
        "ts": "1565708789.003600",
        "username": "Alexander Schwank (Prospela Mentors (beta))",
        "icons": {
            "image_48": "https:\/\/s3-us-west-2.amazonaws.com\/slack-files2\/bot_icons\/2019-08-13\/724580462756_48.png"
        },
        "bot_id": "B6CS60LDU"
    },
    {
        "type": "message",
        "subtype": "bot_message",
        "text": "We don't have a given brief. And we're not getting anymore details except for the marking grid.",
        "ts": "1565708841.003700",
        "username": "Janies (Mentee)",
        "icons": {
            "image_48": "https:\/\/s3-us-west-2.amazonaws.com\/slack-files2\/bot_icons\/2019-08-13\/724581773988_48.png"
        },
        "bot_id": "B6CS60LDU"
    },
    {
        "type": "message",
        "subtype": "bot_message",
        "text": "it not only helps you but also the client as they think about it again which makes their idea\/plan even clearer",
        "ts": "1565708847.003800",
        "username": "Alexander Schwank (Prospela Mentors (beta))",
        "icons": {
            "image_48": "https:\/\/s3-us-west-2.amazonaws.com\/slack-files2\/bot_icons\/2019-08-13\/713606442819_48.png"
        },
        "bot_id": "B6CS60LDU"
    },
    {
        "type": "message",
        "subtype": "bot_message",
        "text": "oh :disappointed:",
        "ts": "1565708855.003900",
        "username": "Alexander Schwank (Prospela Mentors (beta))",
        "icons": {
            "image_48": "https:\/\/s3-us-west-2.amazonaws.com\/slack-files2\/bot_icons\/2019-08-13\/724582167060_48.png"
        },
        "bot_id": "B6CS60LDU"
    },
    {
        "type": "message",
        "subtype": "bot_message",
        "text": "The marking grid focuses on analysis, design and basically how you solve the problem",
        "ts": "1565708876.004000",
        "username": "Janies (Mentee)",
        "icons": {
            "image_48": "https:\/\/s3-us-west-2.amazonaws.com\/slack-files2\/bot_icons\/2019-08-13\/713607140051_48.png"
        },
        "bot_id": "B6CS60LDU"
    },
    {
        "type": "message",
        "subtype": "bot_message",
        "text": "So yeah.. it's a completely made up senario",
        "ts": "1565708893.004100",
        "username": "Janies (Mentee)",
        "icons": {
            "image_48": "https:\/\/s3-us-west-2.amazonaws.com\/slack-files2\/bot_icons\/2019-08-13\/718673288481_48.png"
        },
        "bot_id": "B6CS60LDU"
    },
    {
        "type": "message",
        "subtype": "bot_message",
        "text": "okay, so by framing the scenario the right way, you're free to do pretty much anything you want?",
        "ts": "1565708982.004200",
        "username": "Alexander Schwank (Prospela Mentors (beta))",
        "icons": {
            "image_48": "https:\/\/s3-us-west-2.amazonaws.com\/slack-files2\/bot_icons\/2019-08-13\/718675600193_48.png"
        },
        "bot_id": "B6CS60LDU"
    },
    {
        "type": "message",
        "subtype": "bot_message",
        "text": "Yup, pretty much",
        "ts": "1565709119.004300",
        "username": "Janies (Mentee)",
        "icons": {
            "image_48": "https:\/\/s3-us-west-2.amazonaws.com\/slack-files2\/bot_icons\/2019-08-13\/727203233622_48.png"
        },
        "bot_id": "B6CS60LDU"
    },
    {
        "type": "message",
        "subtype": "bot_message",
        "text": "cool",
        "ts": "1565709432.004400",
        "username": "Alexander Schwank (Prospela Mentors (beta))",
        "icons": {
            "image_48": "https:\/\/s3-us-west-2.amazonaws.com\/slack-files2\/bot_icons\/2019-08-13\/713622369650_48.png"
        },
        "bot_id": "B6CS60LDU"
    }
]