[
    {
        "type": "message",
        "subtype": "bot_message",
        "text": "aha",
        "ts": "1550854821.000100",
        "username": "Lucy (Prospela Mentors (beta))",
        "icons": {
            "image_48": "https:\/\/s3-us-west-2.amazonaws.com\/slack-files2\/bot_icons\/2019-02-22\/559468322359_48.png"
        },
        "bot_id": "B6CS60LDU"
    },
    {
        "type": "message",
        "subtype": "bot_message",
        "text": "What is your MFP?",
        "ts": "1550854830.000200",
        "username": "Lucy (Prospela Mentors (beta))",
        "icons": {
            "image_48": "https:\/\/s3-us-west-2.amazonaws.com\/slack-files2\/bot_icons\/2019-02-22\/557825731665_48.png"
        },
        "bot_id": "B6CS60LDU"
    },
    {
        "type": "message",
        "subtype": "bot_message",
        "text": "Its on astrology through the ages it's going to be a 2d animation ",
        "ts": "1550854949.000300",
        "username": "Guian (Prospela Students (beta))",
        "icons": {
            "image_48": "https:\/\/s3-us-west-2.amazonaws.com\/slack-files2\/bot_icons\/2019-02-22\/557828442257_48.png"
        },
        "bot_id": "B6CS60LDU"
    },
    {
        "type": "message",
        "subtype": "bot_message",
        "text": "Ooh that sounds really interesting.  I’ll look forward to seeing it :slightly_smiling_face:",
        "ts": "1550854990.000400",
        "username": "Lucy (Prospela Mentors (beta))",
        "icons": {
            "image_48": "https:\/\/s3-us-west-2.amazonaws.com\/slack-files2\/bot_icons\/2019-02-22\/559835410230_48.png"
        },
        "bot_id": "B6CS60LDU"
    },
    {
        "type": "message",
        "subtype": "bot_message",
        "text": "Are you working on it on your own or as part of a team?",
        "ts": "1550854995.000500",
        "username": "Lucy (Prospela Mentors (beta))",
        "icons": {
            "image_48": "https:\/\/s3-us-west-2.amazonaws.com\/slack-files2\/bot_icons\/2019-02-22\/558403645698_48.png"
        },
        "bot_id": "B6CS60LDU"
    },
    {
        "type": "message",
        "subtype": "bot_message",
        "text": "Ruwnk you, It's a solo project ",
        "ts": "1550861313.000600",
        "username": "Guian (Prospela Students (beta))",
        "icons": {
            "image_48": "https:\/\/s3-us-west-2.amazonaws.com\/slack-files2\/bot_icons\/2019-02-22\/558847472085_48.png"
        },
        "bot_id": "B6CS60LDU"
    }
]