[
    {
        "type": "message",
        "subtype": "bot_message",
        "text": "Cool. Ok we have time ;) ",
        "ts": "1538765665.000100",
        "username": "Davi Stein (Prospela Mentors (beta))",
        "icons": {
            "image_48": "https:\/\/slack-files2.s3-us-west-2.amazonaws.com\/bot_icons\/2018-10-05\/449666962896_48.png"
        },
        "bot_id": "B6CS60LDU"
    },
    {
        "type": "message",
        "subtype": "bot_message",
        "text": "I was busy this week with my year 3 uni students shooting footage for their short 1 minute animation\/vfx films. Find ideas. They storyboarded it, created a rough edit called a animatic, and temp audio track. We then shot in locations this week around London and then they will finalise their edits next week with the new shot footage and start to animate and create the vfx. Exciting ",
        "ts": "1538765841.000100",
        "username": "Davi Stein (Prospela Mentors (beta))",
        "icons": {
            "image_48": "https:\/\/slack-files2.s3-us-west-2.amazonaws.com\/bot_icons\/2018-10-05\/450592463509_48.png"
        },
        "bot_id": "B6CS60LDU"
    },
    {
        "type": "message",
        "text": "",
        "files": [
            {
                "id": "FD7KPQQEL",
                "created": 1538765882,
                "timestamp": 1538765882,
                "name": "Image from iOS.jpg",
                "title": "Image from iOS",
                "mimetype": "image\/jpeg",
                "filetype": "jpg",
                "pretty_type": "JPEG",
                "user": "U6D2VCN07",
                "editable": false,
                "size": 6463656,
                "mode": "hosted",
                "is_external": false,
                "external_type": "",
                "is_public": true,
                "public_url_shared": false,
                "display_as_bot": false,
                "username": "",
                "url_private": "https:\/\/files.slack.com\/files-pri\/T4UUTPV18-FD7KPQQEL\/image_from_ios.jpg?t=xoxe-164979811042-1081742544354-1080362743317-fee6284c0ee20406565ca4cadf37d845",
                "url_private_download": "https:\/\/files.slack.com\/files-pri\/T4UUTPV18-FD7KPQQEL\/download\/image_from_ios.jpg?t=xoxe-164979811042-1081742544354-1080362743317-fee6284c0ee20406565ca4cadf37d845",
                "thumb_64": "https:\/\/files.slack.com\/files-tmb\/T4UUTPV18-FD7KPQQEL-19c9610430\/image_from_ios_64.jpg?t=xoxe-164979811042-1081742544354-1080362743317-fee6284c0ee20406565ca4cadf37d845",
                "thumb_80": "https:\/\/files.slack.com\/files-tmb\/T4UUTPV18-FD7KPQQEL-19c9610430\/image_from_ios_80.jpg?t=xoxe-164979811042-1081742544354-1080362743317-fee6284c0ee20406565ca4cadf37d845",
                "thumb_360": "https:\/\/files.slack.com\/files-tmb\/T4UUTPV18-FD7KPQQEL-19c9610430\/image_from_ios_360.jpg?t=xoxe-164979811042-1081742544354-1080362743317-fee6284c0ee20406565ca4cadf37d845",
                "thumb_360_w": 360,
                "thumb_360_h": 270,
                "thumb_480": "https:\/\/files.slack.com\/files-tmb\/T4UUTPV18-FD7KPQQEL-19c9610430\/image_from_ios_480.jpg?t=xoxe-164979811042-1081742544354-1080362743317-fee6284c0ee20406565ca4cadf37d845",
                "thumb_480_w": 480,
                "thumb_480_h": 360,
                "thumb_160": "https:\/\/files.slack.com\/files-tmb\/T4UUTPV18-FD7KPQQEL-19c9610430\/image_from_ios_160.jpg?t=xoxe-164979811042-1081742544354-1080362743317-fee6284c0ee20406565ca4cadf37d845",
                "thumb_720": "https:\/\/files.slack.com\/files-tmb\/T4UUTPV18-FD7KPQQEL-19c9610430\/image_from_ios_720.jpg?t=xoxe-164979811042-1081742544354-1080362743317-fee6284c0ee20406565ca4cadf37d845",
                "thumb_720_w": 720,
                "thumb_720_h": 540,
                "thumb_800": "https:\/\/files.slack.com\/files-tmb\/T4UUTPV18-FD7KPQQEL-19c9610430\/image_from_ios_800.jpg?t=xoxe-164979811042-1081742544354-1080362743317-fee6284c0ee20406565ca4cadf37d845",
                "thumb_800_w": 800,
                "thumb_800_h": 600,
                "thumb_960": "https:\/\/files.slack.com\/files-tmb\/T4UUTPV18-FD7KPQQEL-19c9610430\/image_from_ios_960.jpg?t=xoxe-164979811042-1081742544354-1080362743317-fee6284c0ee20406565ca4cadf37d845",
                "thumb_960_w": 960,
                "thumb_960_h": 720,
                "thumb_1024": "https:\/\/files.slack.com\/files-tmb\/T4UUTPV18-FD7KPQQEL-19c9610430\/image_from_ios_1024.jpg?t=xoxe-164979811042-1081742544354-1080362743317-fee6284c0ee20406565ca4cadf37d845",
                "thumb_1024_w": 1024,
                "thumb_1024_h": 768,
                "image_exif_rotation": 1,
                "original_w": 4032,
                "original_h": 3024,
                "permalink": "https:\/\/prospela.slack.com\/files\/U6D2VCN07\/FD7KPQQEL\/image_from_ios.jpg",
                "permalink_public": "https:\/\/slack-files.com\/T4UUTPV18-FD7KPQQEL-da89462c1a",
                "is_starred": false,
                "has_rich_preview": false
            }
        ],
        "upload": true,
        "user": "U6D2VCN07",
        "display_as_bot": false,
        "ts": "1538765890.000100"
    },
    {
        "type": "message",
        "text": "",
        "files": [
            {
                "id": "FD7PN2A4R",
                "created": 1538765962,
                "timestamp": 1538765962,
                "name": "Image from iOS.jpg",
                "title": "Image from iOS",
                "mimetype": "image\/jpeg",
                "filetype": "jpg",
                "pretty_type": "JPEG",
                "user": "U6D2VCN07",
                "editable": false,
                "size": 6038317,
                "mode": "hosted",
                "is_external": false,
                "external_type": "",
                "is_public": true,
                "public_url_shared": false,
                "display_as_bot": false,
                "username": "",
                "url_private": "https:\/\/files.slack.com\/files-pri\/T4UUTPV18-FD7PN2A4R\/image_from_ios.jpg?t=xoxe-164979811042-1081742544354-1080362743317-fee6284c0ee20406565ca4cadf37d845",
                "url_private_download": "https:\/\/files.slack.com\/files-pri\/T4UUTPV18-FD7PN2A4R\/download\/image_from_ios.jpg?t=xoxe-164979811042-1081742544354-1080362743317-fee6284c0ee20406565ca4cadf37d845",
                "thumb_64": "https:\/\/files.slack.com\/files-tmb\/T4UUTPV18-FD7PN2A4R-c486740148\/image_from_ios_64.jpg?t=xoxe-164979811042-1081742544354-1080362743317-fee6284c0ee20406565ca4cadf37d845",
                "thumb_80": "https:\/\/files.slack.com\/files-tmb\/T4UUTPV18-FD7PN2A4R-c486740148\/image_from_ios_80.jpg?t=xoxe-164979811042-1081742544354-1080362743317-fee6284c0ee20406565ca4cadf37d845",
                "thumb_360": "https:\/\/files.slack.com\/files-tmb\/T4UUTPV18-FD7PN2A4R-c486740148\/image_from_ios_360.jpg?t=xoxe-164979811042-1081742544354-1080362743317-fee6284c0ee20406565ca4cadf37d845",
                "thumb_360_w": 360,
                "thumb_360_h": 270,
                "thumb_480": "https:\/\/files.slack.com\/files-tmb\/T4UUTPV18-FD7PN2A4R-c486740148\/image_from_ios_480.jpg?t=xoxe-164979811042-1081742544354-1080362743317-fee6284c0ee20406565ca4cadf37d845",
                "thumb_480_w": 480,
                "thumb_480_h": 360,
                "thumb_160": "https:\/\/files.slack.com\/files-tmb\/T4UUTPV18-FD7PN2A4R-c486740148\/image_from_ios_160.jpg?t=xoxe-164979811042-1081742544354-1080362743317-fee6284c0ee20406565ca4cadf37d845",
                "thumb_720": "https:\/\/files.slack.com\/files-tmb\/T4UUTPV18-FD7PN2A4R-c486740148\/image_from_ios_720.jpg?t=xoxe-164979811042-1081742544354-1080362743317-fee6284c0ee20406565ca4cadf37d845",
                "thumb_720_w": 720,
                "thumb_720_h": 540,
                "thumb_800": "https:\/\/files.slack.com\/files-tmb\/T4UUTPV18-FD7PN2A4R-c486740148\/image_from_ios_800.jpg?t=xoxe-164979811042-1081742544354-1080362743317-fee6284c0ee20406565ca4cadf37d845",
                "thumb_800_w": 800,
                "thumb_800_h": 600,
                "thumb_960": "https:\/\/files.slack.com\/files-tmb\/T4UUTPV18-FD7PN2A4R-c486740148\/image_from_ios_960.jpg?t=xoxe-164979811042-1081742544354-1080362743317-fee6284c0ee20406565ca4cadf37d845",
                "thumb_960_w": 960,
                "thumb_960_h": 720,
                "thumb_1024": "https:\/\/files.slack.com\/files-tmb\/T4UUTPV18-FD7PN2A4R-c486740148\/image_from_ios_1024.jpg?t=xoxe-164979811042-1081742544354-1080362743317-fee6284c0ee20406565ca4cadf37d845",
                "thumb_1024_w": 1024,
                "thumb_1024_h": 768,
                "image_exif_rotation": 1,
                "original_w": 4032,
                "original_h": 3024,
                "permalink": "https:\/\/prospela.slack.com\/files\/U6D2VCN07\/FD7PN2A4R\/image_from_ios.jpg",
                "permalink_public": "https:\/\/slack-files.com\/T4UUTPV18-FD7PN2A4R-01d1a8aadc",
                "is_starred": false,
                "has_rich_preview": false
            }
        ],
        "upload": true,
        "user": "U6D2VCN07",
        "display_as_bot": false,
        "ts": "1538765969.000100"
    },
    {
        "type": "message",
        "text": "",
        "files": [
            {
                "id": "FD7KR79R6",
                "created": 1538765981,
                "timestamp": 1538765981,
                "name": "Image from iOS.jpg",
                "title": "Image from iOS",
                "mimetype": "image\/jpeg",
                "filetype": "jpg",
                "pretty_type": "JPEG",
                "user": "U6D2VCN07",
                "editable": false,
                "size": 6722705,
                "mode": "hosted",
                "is_external": false,
                "external_type": "",
                "is_public": true,
                "public_url_shared": false,
                "display_as_bot": false,
                "username": "",
                "url_private": "https:\/\/files.slack.com\/files-pri\/T4UUTPV18-FD7KR79R6\/image_from_ios.jpg?t=xoxe-164979811042-1081742544354-1080362743317-fee6284c0ee20406565ca4cadf37d845",
                "url_private_download": "https:\/\/files.slack.com\/files-pri\/T4UUTPV18-FD7KR79R6\/download\/image_from_ios.jpg?t=xoxe-164979811042-1081742544354-1080362743317-fee6284c0ee20406565ca4cadf37d845",
                "thumb_64": "https:\/\/files.slack.com\/files-tmb\/T4UUTPV18-FD7KR79R6-81d2f5bcdc\/image_from_ios_64.jpg?t=xoxe-164979811042-1081742544354-1080362743317-fee6284c0ee20406565ca4cadf37d845",
                "thumb_80": "https:\/\/files.slack.com\/files-tmb\/T4UUTPV18-FD7KR79R6-81d2f5bcdc\/image_from_ios_80.jpg?t=xoxe-164979811042-1081742544354-1080362743317-fee6284c0ee20406565ca4cadf37d845",
                "thumb_360": "https:\/\/files.slack.com\/files-tmb\/T4UUTPV18-FD7KR79R6-81d2f5bcdc\/image_from_ios_360.jpg?t=xoxe-164979811042-1081742544354-1080362743317-fee6284c0ee20406565ca4cadf37d845",
                "thumb_360_w": 360,
                "thumb_360_h": 270,
                "thumb_480": "https:\/\/files.slack.com\/files-tmb\/T4UUTPV18-FD7KR79R6-81d2f5bcdc\/image_from_ios_480.jpg?t=xoxe-164979811042-1081742544354-1080362743317-fee6284c0ee20406565ca4cadf37d845",
                "thumb_480_w": 480,
                "thumb_480_h": 360,
                "thumb_160": "https:\/\/files.slack.com\/files-tmb\/T4UUTPV18-FD7KR79R6-81d2f5bcdc\/image_from_ios_160.jpg?t=xoxe-164979811042-1081742544354-1080362743317-fee6284c0ee20406565ca4cadf37d845",
                "thumb_720": "https:\/\/files.slack.com\/files-tmb\/T4UUTPV18-FD7KR79R6-81d2f5bcdc\/image_from_ios_720.jpg?t=xoxe-164979811042-1081742544354-1080362743317-fee6284c0ee20406565ca4cadf37d845",
                "thumb_720_w": 720,
                "thumb_720_h": 540,
                "thumb_800": "https:\/\/files.slack.com\/files-tmb\/T4UUTPV18-FD7KR79R6-81d2f5bcdc\/image_from_ios_800.jpg?t=xoxe-164979811042-1081742544354-1080362743317-fee6284c0ee20406565ca4cadf37d845",
                "thumb_800_w": 800,
                "thumb_800_h": 600,
                "thumb_960": "https:\/\/files.slack.com\/files-tmb\/T4UUTPV18-FD7KR79R6-81d2f5bcdc\/image_from_ios_960.jpg?t=xoxe-164979811042-1081742544354-1080362743317-fee6284c0ee20406565ca4cadf37d845",
                "thumb_960_w": 960,
                "thumb_960_h": 720,
                "thumb_1024": "https:\/\/files.slack.com\/files-tmb\/T4UUTPV18-FD7KR79R6-81d2f5bcdc\/image_from_ios_1024.jpg?t=xoxe-164979811042-1081742544354-1080362743317-fee6284c0ee20406565ca4cadf37d845",
                "thumb_1024_w": 1024,
                "thumb_1024_h": 768,
                "image_exif_rotation": 1,
                "original_w": 4032,
                "original_h": 3024,
                "permalink": "https:\/\/prospela.slack.com\/files\/U6D2VCN07\/FD7KR79R6\/image_from_ios.jpg",
                "permalink_public": "https:\/\/slack-files.com\/T4UUTPV18-FD7KR79R6-587fcc3748",
                "is_starred": false,
                "has_rich_preview": false
            }
        ],
        "upload": true,
        "user": "U6D2VCN07",
        "display_as_bot": false,
        "ts": "1538765989.000100"
    },
    {
        "type": "message",
        "subtype": "bot_message",
        "text": "This film will have a futuristic CG robot that goes around cleaning up after people. But then gets harassed by a dude, and gets a  bottle thrown at it and turns angry and switches gear and ‘cleans up’ the dude by putting him Ina huge skip , in a comical manner. ",
        "ts": "1538766094.000100",
        "username": "Davi Stein (Prospela Mentors (beta))",
        "icons": {
            "image_48": "https:\/\/slack-files2.s3-us-west-2.amazonaws.com\/bot_icons\/2018-10-05\/450315151347_48.png"
        },
        "bot_id": "B6CS60LDU"
    },
    {
        "type": "message",
        "text": "",
        "files": [
            {
                "id": "FD7KUPY6L",
                "created": 1538766236,
                "timestamp": 1538766236,
                "name": "Image from iOS.jpg",
                "title": "Image from iOS",
                "mimetype": "image\/jpeg",
                "filetype": "jpg",
                "pretty_type": "JPEG",
                "user": "U6D2VCN07",
                "editable": false,
                "size": 8514910,
                "mode": "hosted",
                "is_external": false,
                "external_type": "",
                "is_public": true,
                "public_url_shared": false,
                "display_as_bot": false,
                "username": "",
                "url_private": "https:\/\/files.slack.com\/files-pri\/T4UUTPV18-FD7KUPY6L\/image_from_ios.jpg?t=xoxe-164979811042-1081742544354-1080362743317-fee6284c0ee20406565ca4cadf37d845",
                "url_private_download": "https:\/\/files.slack.com\/files-pri\/T4UUTPV18-FD7KUPY6L\/download\/image_from_ios.jpg?t=xoxe-164979811042-1081742544354-1080362743317-fee6284c0ee20406565ca4cadf37d845",
                "thumb_64": "https:\/\/files.slack.com\/files-tmb\/T4UUTPV18-FD7KUPY6L-6103b0fd6f\/image_from_ios_64.jpg?t=xoxe-164979811042-1081742544354-1080362743317-fee6284c0ee20406565ca4cadf37d845",
                "thumb_80": "https:\/\/files.slack.com\/files-tmb\/T4UUTPV18-FD7KUPY6L-6103b0fd6f\/image_from_ios_80.jpg?t=xoxe-164979811042-1081742544354-1080362743317-fee6284c0ee20406565ca4cadf37d845",
                "thumb_360": "https:\/\/files.slack.com\/files-tmb\/T4UUTPV18-FD7KUPY6L-6103b0fd6f\/image_from_ios_360.jpg?t=xoxe-164979811042-1081742544354-1080362743317-fee6284c0ee20406565ca4cadf37d845",
                "thumb_360_w": 360,
                "thumb_360_h": 270,
                "thumb_480": "https:\/\/files.slack.com\/files-tmb\/T4UUTPV18-FD7KUPY6L-6103b0fd6f\/image_from_ios_480.jpg?t=xoxe-164979811042-1081742544354-1080362743317-fee6284c0ee20406565ca4cadf37d845",
                "thumb_480_w": 480,
                "thumb_480_h": 360,
                "thumb_160": "https:\/\/files.slack.com\/files-tmb\/T4UUTPV18-FD7KUPY6L-6103b0fd6f\/image_from_ios_160.jpg?t=xoxe-164979811042-1081742544354-1080362743317-fee6284c0ee20406565ca4cadf37d845",
                "thumb_720": "https:\/\/files.slack.com\/files-tmb\/T4UUTPV18-FD7KUPY6L-6103b0fd6f\/image_from_ios_720.jpg?t=xoxe-164979811042-1081742544354-1080362743317-fee6284c0ee20406565ca4cadf37d845",
                "thumb_720_w": 720,
                "thumb_720_h": 540,
                "thumb_800": "https:\/\/files.slack.com\/files-tmb\/T4UUTPV18-FD7KUPY6L-6103b0fd6f\/image_from_ios_800.jpg?t=xoxe-164979811042-1081742544354-1080362743317-fee6284c0ee20406565ca4cadf37d845",
                "thumb_800_w": 800,
                "thumb_800_h": 600,
                "thumb_960": "https:\/\/files.slack.com\/files-tmb\/T4UUTPV18-FD7KUPY6L-6103b0fd6f\/image_from_ios_960.jpg?t=xoxe-164979811042-1081742544354-1080362743317-fee6284c0ee20406565ca4cadf37d845",
                "thumb_960_w": 960,
                "thumb_960_h": 720,
                "thumb_1024": "https:\/\/files.slack.com\/files-tmb\/T4UUTPV18-FD7KUPY6L-6103b0fd6f\/image_from_ios_1024.jpg?t=xoxe-164979811042-1081742544354-1080362743317-fee6284c0ee20406565ca4cadf37d845",
                "thumb_1024_w": 1024,
                "thumb_1024_h": 768,
                "image_exif_rotation": 1,
                "original_w": 4032,
                "original_h": 3024,
                "permalink": "https:\/\/prospela.slack.com\/files\/U6D2VCN07\/FD7KUPY6L\/image_from_ios.jpg",
                "permalink_public": "https:\/\/slack-files.com\/T4UUTPV18-FD7KUPY6L-88848302b1",
                "is_starred": false,
                "has_rich_preview": false
            }
        ],
        "upload": true,
        "user": "U6D2VCN07",
        "display_as_bot": false,
        "ts": "1538766245.000100"
    },
    {
        "type": "message",
        "text": "",
        "files": [
            {
                "id": "FD8BZ0Y5R",
                "created": 1538773938,
                "timestamp": 1538773938,
                "name": "Image from iOS.MOV",
                "title": "Image from iOS",
                "mimetype": "video\/quicktime",
                "filetype": "mov",
                "pretty_type": "QuickTime Movie",
                "user": "U6D2VCN07",
                "editable": false,
                "size": 8180948,
                "mode": "hosted",
                "is_external": false,
                "external_type": "",
                "is_public": true,
                "public_url_shared": false,
                "display_as_bot": false,
                "username": "",
                "url_private": "https:\/\/files.slack.com\/files-pri\/T4UUTPV18-FD8BZ0Y5R\/image_from_ios.mov?t=xoxe-164979811042-1081742544354-1080362743317-fee6284c0ee20406565ca4cadf37d845",
                "url_private_download": "https:\/\/files.slack.com\/files-pri\/T4UUTPV18-FD8BZ0Y5R\/download\/image_from_ios.mov?t=xoxe-164979811042-1081742544354-1080362743317-fee6284c0ee20406565ca4cadf37d845",
                "permalink": "https:\/\/prospela.slack.com\/files\/U6D2VCN07\/FD8BZ0Y5R\/image_from_ios.mov",
                "permalink_public": "https:\/\/slack-files.com\/T4UUTPV18-FD8BZ0Y5R-03c9735ee7",
                "is_starred": false,
                "has_rich_preview": false
            }
        ],
        "upload": true,
        "user": "U6D2VCN07",
        "display_as_bot": false,
        "ts": "1538773939.000100"
    }
]